stockholm/__init__.py
stockholm/__version__.py
stockholm/currency.py
stockholm/exceptions.py
stockholm/money.py
stockholm/protobuf/__init__.py
stockholm/protobuf/money.proto
stockholm/protobuf/money_pb2.py
stockholm/protobuf/money_pb2.pyi
stockholm/py.typed
stockholm/rate.py
stockholm/types.py
stockholm-0.5.7.dist-info/LICENSE
stockholm-0.5.7.dist-info/METADATA
stockholm-0.5.7.dist-info/WHEEL
stockholm-0.5.7.dist-info/RECORD
