Metadata-Version: 2.1
Name: stockholm
Version: 0.5.7
Summary: Human friendly and flexible package for working with monetary amounts
Home-page: https://github.com/kalaspuff/stockholm
License: MIT
Keywords: money,monetary amount,monetary value,currency,formatting,protobuf,protocol buffers,graphql,money graphql,protobuf money,protocol buffers money,json,python money,monetary object,python money class,finance,fintech
Author: Carl Oscar Aaro
Author-email: hello@carloscar.com
Requires-Python: >=3.8,<4.0
Classifier: Development Status :: 4 - Beta
Classifier: Intended Audience :: Developers
Classifier: Intended Audience :: Financial and Insurance Industry
Classifier: License :: OSI Approved :: MIT License
Classifier: Programming Language :: Python
Classifier: Programming Language :: Python :: 3
Classifier: Programming Language :: Python :: 3.8
Classifier: Programming Language :: Python :: 3.9
Classifier: Programming Language :: Python :: 3.10
Classifier: Programming Language :: Python :: 3.11
Classifier: Programming Language :: Python :: 3.12
Classifier: Topic :: Office/Business :: Financial
Classifier: Topic :: Software Development :: Libraries
Classifier: Typing :: Typed
Provides-Extra: protobuf
Requires-Dist: protobuf (>=3.20.0,<5.0.0) ; extra == "protobuf"
Requires-Dist: typing-extensions (>=4.7.0) ; python_full_version <= "3.10.0"
Project-URL: Repository, https://github.com/kalaspuff/stockholm
